poetry_brew/__init__.py
poetry_brew/plugin.py
poetry_brew/templates.py
poetry_brew-1.0.3.dist-info/entry_points.txt
poetry_brew-1.0.3.dist-info/WHEEL
poetry_brew-1.0.3.dist-info/METADATA
poetry_brew-1.0.3.dist-info/LICENSE.md
poetry_brew-1.0.3.dist-info/RECORD
