Metadata-Version: 2.1
Name: poetry-brew
Version: 1.0.3
Summary: Generate Homebrew formulae for Poetry projects
Home-page: https://github.com/celsiusnarhwal/poetry-brew
License: MIT
Author: celsius narhwal
Author-email: hello@celsiusnarhwal.dev
Requires-Python: >=3.10,<4.0
Classifier: License :: OSI Approved :: MIT License
Classifier: Programming Language :: Python :: 3
Classifier: Programming Language :: Python :: 3.10
Classifier: Programming Language :: Python :: 3.11
Requires-Dist: dict-deep (>=4.1.2,<5.0.0)
Requires-Dist: jinja2 (>=3.1.2,<4.0.0)
Requires-Dist: poetry (>=1.2,<2.0)
Requires-Dist: pydantic (>=1.10.3,<2.0.0)
Requires-Dist: requests (>=2.28.1,<3.0.0)
Project-URL: Repository, https://github.com/celsiusnarhwal/poetry-brew
